womm/Dockerfile
womm/__init__.py
womm/__main__.py
womm/bestsh
womm/cluster-setup.yml
womm/common.py
womm/parallel
womm/parallel.py
womm/setup.py
womm/sudo
womm/sudo.c
womm/task-deployment.yml
womm/trapper
womm-0.1.6.dist-info/LICENSE
womm-0.1.6.dist-info/METADATA
womm-0.1.6.dist-info/WHEEL
womm-0.1.6.dist-info/entry_points.txt
womm-0.1.6.dist-info/top_level.txt
womm-0.1.6.dist-info/RECORD
