Metadata-Version: 2.1
Name: womm
Version: 0.1.6
Summary: Works On My Machine - quick-set glue for scaling scripts with kubernetes
Home-page: https://github.com/rhelmot/womm
License: zlib
Requires-Python: >=3.6
License-File: LICENSE
Requires-Dist: psutil
Requires-Dist: tabulate
Requires-Dist: python-dateutil
